{
  "about-separator": {
    "title": "About Us",
    "type": "separator"
  },
  "index": "About",
  "vision": {
    "title": "Vision",
    "display": "hidden"
  },
  "team": "Team",
  "wall-of-love": {
    "theme": {
      "toc": false,
      "layout": "full"
    }
  },
  "acknowledgements": "",
  "handbook-separator": {
    "title": "Handbook",
    "type": "separator"
  },
  "how-we-work": {},
  "faq-separator": {
    "title": "Frequently Asked Questions",
    "type": "separator"
  },
  "faq": "FAQ"
}
